apron
pyapron
